discordbook/__init__.py
discordbook/alpha_book.py
discordbook/book.py
discordbook/chapter.py
discordbook-0.2.4.dist-info/LICENSE.txt
discordbook-0.2.4.dist-info/METADATA
discordbook-0.2.4.dist-info/WHEEL
discordbook-0.2.4.dist-info/top_level.txt
discordbook-0.2.4.dist-info/RECORD
