Metadata-Version: 2.1
Name: discordbook
Version: 0.2.4
Summary: A Discord.py module to facilitate easier viewing for large amounts of content.
Home-page: https://github.com/cvxluo/discordbook
Author: Charlie Luo
Author-email: charliexluo@gmail.com
License: UNKNOWN
Platform: UNKNOWN
Classifier: Programming Language :: Python :: 3
Classifier: License :: OSI Approved :: MIT License
Classifier: Operating System :: OS Independent
Requires-Python: >=3.5
